OpenSankey-0.9.12.data/scripts/app.py
opensankey/__init__.py
opensankey/app.py
opensankey/setup.cfg
opensankey/doc/__init__.py
opensankey/doc/make.bat
opensankey/doc/views.py
opensankey/server/__init__.py
opensankey/server/converter.py
opensankey/server/sankeymatic.py
opensankey/server/sankeymatic_utils.py
opensankey/server/views.py
opensankey/tests/__init__.py
opensankey/tests/test_dict_results.py
OpenSankey-0.9.12.dist-info/LICENSE
OpenSankey-0.9.12.dist-info/METADATA
OpenSankey-0.9.12.dist-info/WHEEL
OpenSankey-0.9.12.dist-info/top_level.txt
OpenSankey-0.9.12.dist-info/RECORD
