Metadata-Version: 2.1
Name: OpenSankey
Version: 0.9.12
Summary: OpenSankey
Home-page: https://gitlab.com/terriflux-public/OpenSankey
Author: TerriFlux
Author-email: contact@terriflux.fr
License: MIT
License-File: LICENSE
